{
	"status": "y",
	"info": "",
	"data": [{
		"id": 1675,
		"name": "紫藤叶"

	}, {
		"id": 1620,
		"name": "甜橘叶"

	}, {
		"id": 1599,
		"name": "石楠叶 "

	}, {
		"id": 1586,
		"name": "桑叶(霜)"

	}, {
		"id": 1546,
		"name": "木芙蓉叶"

	}, {
		"id": 1518,
		"name": "莱菔叶"

	}, {
		"id": 1504,
		"name": "金橘叶"

	}, {
		"id": 1440,
		"name": "丁香叶"
	}, {
		"id": 1429,
		"name": "大叶紫珠"

	}, {
		"id": 1419,
		"name": "臭梧桐叶"
	}, {
		"id": 1327,
		"name": "竹叶青"
	}, {
		"id": 1051,
		"name": "剑叶耳草"

	}, {
		"id": 1054,
		"name": "贯叶连翘"

	}, {
		"id": 1062,
		"name": "苕叶细辛"

	}, {
		"id": 1064,
		"name": "大叶茜草"
	}, {
		"id": 1075,
		"name": "二叶兜被兰"

	}, {
		"id": 1140,
		"name": "七叶一把伞"
	}, {
		"id": 1175,
		"name": "一叶萩"
	}, {
		"id": 1180,
		"name": "半截叶"

	}, {
		"id": 259,
		"name": "枸骨叶"

	}, {
		"id": 263,
		"name": "杜仲叶"
	}, {
		"id": 270,
		"name": "三叶青"

	}, {
		"id": 276,
		"name": "月桂叶"
	}, {
		"id": 296,
		"name": "白背叶"
	}]
}